LICENSE
MANIFEST.in
README.md
setup.py
lim_sample.egg-info/PKG-INFO
lim_sample.egg-info/SOURCES.txt
lim_sample.egg-info/dependency_links.txt
lim_sample.egg-info/requires.txt
lim_sample.egg-info/top_level.txt
sample/__init__.py
sample/_training.py
sample/collapsible_params.html
sample/gui.py
sample/hinge.py
sample/ipython.py
sample/optimize.py
sample/plots.py
sample/psycho.py
sample/sample.py
sample/vid.py
sample/web_audio.html
sample/beatsdrop/__init__.py
sample/beatsdrop/decision.py
sample/beatsdrop/regression.py
sample/beatsdrop/sample.py
sample/evaluation/__init__.py
sample/evaluation/metrics.py
sample/evaluation/random.py
sample/sms/__init__.py
sample/sms/dsp.py
sample/sms/mm.py
sample/sms/sm.py
sample/utils/__init__.py
sample/utils/dsp.py
sample/utils/learn.py
sample/widgets/__init__.py
sample/widgets/analysis.py
sample/widgets/audio.py
sample/widgets/audioload.py
sample/widgets/images.py
sample/widgets/main.py
sample/widgets/pyplot.py
sample/widgets/responsive.py
sample/widgets/sample.py
sample/widgets/settings.py
sample/widgets/userfiles.py
sample/widgets/utils.py