Metadata-Version: 2.1
Name: lim-sample
Version: 2.1.0
Summary: Package for the SAMPLE method
Home-page: https://github.com/limunimi/sample
Author: Marco Tiraboschi
Author-email: marco.tiraboschi@unimi.it
Maintainer: Marco Tiraboschi
Maintainer-email: marco.tiraboschi@unimi.it
Classifier: Programming Language :: Python :: 3
Classifier: License :: OSI Approved :: MIT License
Classifier: Operating System :: OS Independent
Requires-Python: >=3.6
Provides-Extra: gui
Provides-Extra: plots
Provides-Extra: notebooks
Provides-Extra: scripts-beatsdrop
Provides-Extra: scripts-cim22
Provides-Extra: test
Provides-Extra: docs
Provides-Extra: style
Provides-Extra: cov
Provides-Extra: packaging
Provides-Extra: installer
License-File: LICENSE
